ds_validator/__init__.py
ds_validator/decorators.py
ds_validator/exceptions/__init__.py
ds_validator/exceptions/import_errors.py
ds_validator/exceptions/validator_error.py
ds_validator/numpy/__init__.py
ds_validator/numpy/array.py
ds_validator/pandas/__init__.py
ds_validator/pandas/common.py
ds_validator/pandas/dataframe.py
ds_validator/pandas/series.py
ds_validator/pydantic_adapters.py
ds_validator/shape_error_finder.py
ds_validator/torch/__init__.py
ds_validator/torch/tensor.py
ds_validator-0.1.1.dist-info/LICENSE
ds_validator-0.1.1.dist-info/METADATA
ds_validator-0.1.1.dist-info/WHEEL
ds_validator-0.1.1.dist-info/RECORD
